[{"name_iata": "ABE", "name": "Lehigh Valley International Airport", "airlines": {"EV": {"flights": 1876, "delays": 295}, "DL": {"flights": 308, "delays": 16}, "OO": {"flights": 51, "delays": 7}}}, {"name_iata": "ABI", "name": "Abilene Regional Airport", "airlines": {"MQ": {"flights": 2232, "delays": 303}}}, {"name_iata": "ABQ", "name": "Albuquerque International Sunport", "airlines": {"WN": {"flights": 10802, "delays": 2265}, "MQ": {"flights": 457, "delays": 94}, "AA": {"flights": 1824, "delays": 219}, "DL": {"flights": 1238, "delays": 98}, "OO": {"flights": 3257, "delays": 445}, "EV": {"flights": 409, "delays": 54}, "AS": {"flights": 334, "delays": 12}, "B6": {"flights": 271, "delays": 82}, "US": {"flights": 48, "delays": 6}, "UA": {"flights": 340, "delays": 68}}}, {"name_iata": "ABR", "name": "Aberdeen Regional Airport", "airlines": {"OO": {"flights": 663, "delays": 75}}}, {"name_iata": "ABY", "name": "Southwest Georgia Regional Airport", "airlines": {"EV": {"flights": 867, "delays": 137}}}, {"name_iata": "ACK", "name": "Nantucket Memorial Airport", "airlines": {"B6": {"flights": 486, "delays": 113}}}, {"name_iata": "ACT", "name": "Waco Regional Airport", "airlines": {"MQ": {"flights": 519, "delays": 93}, "EV": {"flights": 1020, "delays": 144}}}, {"name_iata": "ACV", "name": "Arcata Airport", "airlines": {"OO": {"flights": 1269, "delays": 281}}}, {"name_iata": "ACY", "name": "Atlantic City International Airport", "airlines": {"NK": {"flights": 3532, "delays": 659}}}, {"name_iata": "ADK", "name": "Adak Airport", "airlines": {"AS": {"flights": 89, "delays": 37}}}, {"name_iata": "ADQ", "name": "Kodiak Airport", "airlines": {"AS": {"flights": 437, "delays": 47}}}, {"name_iata": "AEX", "name": "Alexandria International Airport", "airlines": {"MQ": {"flights": 795, "delays": 143}, "EV": {"flights": 2265, "delays": 332}}}, {"name_iata": "AGS", "name": "Augusta Regional Airport\u00a0(Bush Field)", "airlines": {"EV": {"flights": 1638, "delays": 285}, "DL": {"flights": 696, "delays": 75}, "UA": {"flights": 1, "delays": 0}, "OO": {"flights": 11, "delays": 0}}}, {"name_iata": "AKN", "name": "King Salmon Airport", "airlines": {"AS": {"flights": 63, "delays": 9}}}, {"name_iata": "ALB", "name": "Albany International Airport", "airlines": {"WN": {"flights": 3962, "delays": 530}, "UA": {"flights": 637, "delays": 104}, "US": {"flights": 355, "delays": 42}, "DL": {"flights": 1197, "delays": 139}, "OO": {"flights": 87, "delays": 16}, "EV": {"flights": 717, "delays": 112}, "AA": {"flights": 342, "delays": 32}, "B6": {"flights": 44, "delays": 10}}}, {"name_iata": "ALO", "name": "Waterloo Regional Airport", "airlines": {"MQ": {"flights": 582, "delays": 78}}}, {"name_iata": "AMA", "name": "Rick Husband Amarillo International Airport", "airlines": {"EV": {"flights": 1107, "delays": 130}, "WN": {"flights": 1524, "delays": 197}, "MQ": {"flights": 997, "delays": 190}, "OO": {"flights": 452, "delays": 67}}}, {"name_iata": "ANC", "name": "Ted Stevens Anchorage International Airport", "airlines": {"AS": {"flights": 12046, "delays": 1001}, "DL": {"flights": 2016, "delays": 288}, "US": {"flights": 163, "delays": 19}, "UA": {"flights": 1003, "delays": 382}, "B6": {"flights": 385, "delays": 92}, "AA": {"flights": 268, "delays": 69}}}, {"name_iata": "APN", "name": "Alpena County Regional Airport", "airlines": {"OO": {"flights": 547, "delays": 69}}}, {"name_iata": "ASE", "name": "Aspen-Pitkin County Airport", "airlines": {"OO": {"flights": 2829, "delays": 718}, "MQ": {"flights": 457, "delays": 172}}}, {"name_iata": "ATL", "name": "Hartsfield-Jackson Atlanta International Airport", "airlines": {"EV": {"flights": 56370, "delays": 11048}, "F9": {"flights": 4471, "delays": 1334}, "DL": {"flights": 220790, "delays": 32735}, "OO": {"flights": 4125, "delays": 759}, "US": {"flights": 2891, "delays": 338}, "AA": {"flights": 7388, "delays": 945}, "NK": {"flights": 4312, "delays": 1505}, "WN": {"flights": 39007, "delays": 9243}, "UA": {"flights": 3316, "delays": 845}, "MQ": {"flights": 1181, "delays": 324}, "AS": {"flights": 428, "delays": 64}}}, {"name_iata": "ATW", "name": "Appleton International Airport", "airlines": {"DL": {"flights": 446, "delays": 24}, "EV": {"flights": 1462, "delays": 234}, "OO": {"flights": 857, "delays": 123}}}, {"name_iata": "AUS", "name": "Austin-Bergstrom International Airport", "airlines": {"OO": {"flights": 2860, "delays": 535}, "AA": {"flights": 7834, "delays": 1171}, "B6": {"flights": 2183, "delays": 408}, "UA": {"flights": 4231, "delays": 860}, "DL": {"flights": 3439, "delays": 428}, "WN": {"flights": 17180, "delays": 3155}, "US": {"flights": 460, "delays": 82}, "VX": {"flights": 1371, "delays": 163}, "F9": {"flights": 1208, "delays": 294}, "AS": {"flights": 400, "delays": 63}, "EV": {"flights": 323, "delays": 31}}}, {"name_iata": "AVL", "name": "Asheville Regional Airport", "airlines": {"DL": {"flights": 639, "delays": 76}, "OO": {"flights": 692, "delays": 81}, "EV": {"flights": 1353, "delays": 226}}}, {"name_iata": "AVP", "name": "Wilkes-Barre/Scranton International Airport", "airlines": {"EV": {"flights": 1206, "delays": 173}, "DL": {"flights": 125, "delays": 5}}}, {"name_iata": "AZO", "name": "Kalamazoo/Battle Creek International Airport", "airlines": {"MQ": {"flights": 1190, "delays": 142}, "EV": {"flights": 242, "delays": 37}, "OO": {"flights": 311, "delays": 45}}}, {"name_iata": "BDL", "name": "Bradley International Airport", "airlines": {"EV": {"flights": 1229, "delays": 186}, "DL": {"flights": 4051, "delays": 422}, "B6": {"flights": 3183, "delays": 662}, "UA": {"flights": 556, "delays": 121}, "AA": {"flights": 1796, "delays": 200}, "WN": {"flights": 5909, "delays": 914}, "US": {"flights": 811, "delays": 74}, "MQ": {"flights": 383, "delays": 89}, "OO": {"flights": 519, "delays": 104}}}, {"name_iata": "BET", "name": "Bethel Airport", "airlines": {"AS": {"flights": 880, "delays": 106}}}, {"name_iata": "BFL", "name": "Meadows Field", "airlines": {"OO": {"flights": 2595, "delays": 379}}}, {"name_iata": "BGM", "name": "Greater Binghamton Airport", "airlines": {"EV": {"flights": 197, "delays": 22}, "OO": {"flights": 62, "delays": 7}}}, {"name_iata": "BGR", "name": "Bangor International Airport", "airlines": {"EV": {"flights": 174, "delays": 17}, "DL": {"flights": 189, "delays": 16}}}, {"name_iata": "BHM", "name": "Birmingham-Shuttlesworth International Airport", "airlines": {"MQ": {"flights": 910, "delays": 149}, "DL": {"flights": 3039, "delays": 344}, "AA": {"flights": 222, "delays": 32}, "EV": {"flights": 3178, "delays": 566}, "WN": {"flights": 4104, "delays": 665}, "OO": {"flights": 880, "delays": 175}}}, {"name_iata": "BIL", "name": "Billings Logan International Airport", "airlines": {"OO": {"flights": 1143, "delays": 106}, "UA": {"flights": 649, "delays": 90}, "DL": {"flights": 982, "delays": 42}, "EV": {"flights": 79, "delays": 5}}}, {"name_iata": "BIS", "name": "Bismarck Municipal Airport", "airlines": {"OO": {"flights": 2232, "delays": 302}, "MQ": {"flights": 644, "delays": 105}, "DL": {"flights": 277, "delays": 15}, "F9": {"flights": 101, "delays": 16}, "EV": {"flights": 139, "delays": 14}}}, {"name_iata": "BJI", "name": "Bemidji Regional Airport", "airlines": {"OO": {"flights": 664, "delays": 48}}}, {"name_iata": "BLI", "name": "Bellingham International Airport", "airlines": {"AS": {"flights": 708, "delays": 48}}}, {"name_iata": "BMI", "name": "Central Illinois Regional Airport at Bloomington-Normal", "airlines": {"MQ": {"flights": 1524, "delays": 187}, "EV": {"flights": 985, "delays": 133}, "F9": {"flights": 36, "delays": 21}, "OO": {"flights": 81, "delays": 14}}}, {"name_iata": "BNA", "name": "Nashville International Airport", "airlines": {"DL": {"flights": 4635, "delays": 602}, "EV": {"flights": 2965, "delays": 494}, "AA": {"flights": 3921, "delays": 552}, "OO": {"flights": 2928, "delays": 427}, "WN": {"flights": 26863, "delays": 5288}, "US": {"flights": 668, "delays": 61}, "MQ": {"flights": 3744, "delays": 783}, "F9": {"flights": 321, "delays": 61}, "UA": {"flights": 401, "delays": 66}, "AS": {"flights": 68, "delays": 13}}}, {"name_iata": "BOI", "name": "Boise Airport\u00a0(Boise Air Terminal)", "airlines": {"OO": {"flights": 6263, "delays": 1059}, "US": {"flights": 393, "delays": 50}, "UA": {"flights": 553, "delays": 96}, "WN": {"flights": 2939, "delays": 474}, "DL": {"flights": 1049, "delays": 51}, "AA": {"flights": 357, "delays": 44}}}, {"name_iata": "BOS", "name": "Gen. Edward Lawrence Logan International Airport", "airlines": {"NK": {"flights": 2181, "delays": 556}, "AA": {"flights": 17228, "delays": 2187}, "B6": {"flights": 37250, "delays": 6982}, "DL": {"flights": 13927, "delays": 2448}, "UA": {"flights": 11034, "delays": 2520}, "WN": {"flights": 9735, "delays": 2033}, "US": {"flights": 8416, "delays": 1213}, "EV": {"flights": 2215, "delays": 361}, "VX": {"flights": 1569, "delays": 250}, "AS": {"flights": 1385, "delays": 168}, "OO": {"flights": 253, "delays": 50}}}, {"name_iata": "BPT", "name": "Jack Brooks Regional Airport\u00a0(Southeast Texas Regional)", "airlines": {"EV": {"flights": 489, "delays": 100}, "MQ": {"flights": 421, "delays": 109}}}, {"name_iata": "BQK", "name": "Brunswick Golden Isles Airport", "airlines": {"EV": {"flights": 869, "delays": 116}}}, {"name_iata": "BQN", "name": "Rafael Hern\u00e1ndez Airport", "airlines": {"UA": {"flights": 287, "delays": 117}, "B6": {"flights": 883, "delays": 138}, "NK": {"flights": 162, "delays": 41}}}, {"name_iata": "BRD", "name": "Brainerd Lakes Regional Airport", "airlines": {"OO": {"flights": 582, "delays": 34}}}, {"name_iata": "BRO", "name": "Brownsville/South Padre Island International Airport", "airlines": {"EV": {"flights": 2120, "delays": 245}, "MQ": {"flights": 93, "delays": 27}, "OO": {"flights": 52, "delays": 1}}}, {"name_iata": "BRW", "name": "Wiley Post-Will Rogers Memorial Airport", "airlines": {"AS": {"flights": 828, "delays": 115}}}, {"name_iata": "BTM", "name": "Bert Mooney Airport", "airlines": {"OO": {"flights": 648, "delays": 35}}}, {"name_iata": "BTR", "name": "Baton Rouge Metropolitan Airport", "airlines": {"EV": {"flights": 6165, "delays": 1147}, "MQ": {"flights": 507, "delays": 101}, "DL": {"flights": 315, "delays": 41}, "UA": {"flights": 2, "delays": 2}, "OO": {"flights": 14, "delays": 3}}}, {"name_iata": "BTV", "name": "Burlington International Airport", "airlines": {"B6": {"flights": 997, "delays": 148}, "EV": {"flights": 1702, "delays": 313}, "DL": {"flights": 89, "delays": 7}, "UA": {"flights": 101, "delays": 12}}}, {"name_iata": "BUF", "name": "Buffalo Niagara International Airport", "airlines": {"B6": {"flights": 4015, "delays": 652}, "EV": {"flights": 1607, "delays": 283}, "US": {"flights": 654, "delays": 77}, "UA": {"flights": 503, "delays": 106}, "WN": {"flights": 5760, "delays": 872}, "DL": {"flights": 2381, "delays": 220}, "MQ": {"flights": 936, "delays": 166}, "OO": {"flights": 114, "delays": 27}, "AA": {"flights": 537, "delays": 51}}}, {"name_iata": "BUR", "name": "Bob Hope Airport\u00a0(Hollywood Burbank Airport)", "airlines": {"AS": {"flights": 1011, "delays": 66}, "OO": {"flights": 3968, "delays": 594}, "WN": {"flights": 13266, "delays": 1887}, "B6": {"flights": 329, "delays": 89}}}, {"name_iata": "BWI", "name": "Baltimore-Washington International Airport", "airlines": {"AA": {"flights": 4069, "delays": 621}, "DL": {"flights": 6483, "delays": 809}, "NK": {"flights": 2772, "delays": 782}, "US": {"flights": 1866, "delays": 227}, "WN": {"flights": 62856, "delays": 16383}, "UA": {"flights": 2964, "delays": 618}, "B6": {"flights": 1734, "delays": 220}, "AS": {"flights": 414, "delays": 60}, "MQ": {"flights": 1046, "delays": 245}, "EV": {"flights": 341, "delays": 56}, "OO": {"flights": 1, "delays": 1}}}, {"name_iata": "BZN", "name": "Bozeman Yellowstone International Airport\u00a0(Gallatin Field Airport)", "airlines": {"F9": {"flights": 189, "delays": 24}, "UA": {"flights": 679, "delays": 143}, "DL": {"flights": 1080, "delays": 81}, "OO": {"flights": 1617, "delays": 200}}}, {"name_iata": "CAE", "name": "Columbia Metropolitan Airport", "airlines": {"EV": {"flights": 3849, "delays": 693}, "MQ": {"flights": 162, "delays": 47}, "DL": {"flights": 1013, "delays": 78}, "OO": {"flights": 33, "delays": 9}}}, {"name_iata": "CAK", "name": "Akron-Canton Regional Airport", "airlines": {"WN": {"flights": 3127, "delays": 437}, "EV": {"flights": 1489, "delays": 165}, "DL": {"flights": 1340, "delays": 120}, "OO": {"flights": 44, "delays": 5}}}, {"name_iata": "CDC", "name": "Cedar City Regional Airport", "airlines": {"OO": {"flights": 572, "delays": 54}}}, {"name_iata": "CDV", "name": "Merle K. (Mudhole) Smith Airport", "airlines": {"AS": {"flights": 653, "delays": 87}}}, {"name_iata": "CEC", "name": "Del Norte County Airport\u00a0(Jack McNamara Field)", "airlines": {"OO": {"flights": 174, "delays": 49}}}, {"name_iata": "CHA", "name": "Chattanooga Metropolitan Airport\u00a0(Lovell Field)", "airlines": {"EV": {"flights": 2650, "delays": 413}, "MQ": {"flights": 639, "delays": 146}, "DL": {"flights": 774, "delays": 76}, "OO": {"flights": 69, "delays": 11}}}, {"name_iata": "CHO", "name": "Charlottesville-Albemarle Airport", "airlines": {"OO": {"flights": 990, "delays": 229}, "EV": {"flights": 560, "delays": 85}, "MQ": {"flights": 234, "delays": 62}, "DL": {"flights": 320, "delays": 12}}}, {"name_iata": "CHS", "name": "Charleston International Airport/Charleston AFB", "airlines": {"EV": {"flights": 2600, "delays": 448}, "MQ": {"flights": 486, "delays": 91}, "DL": {"flights": 3586, "delays": 341}, "WN": {"flights": 2352, "delays": 393}, "B6": {"flights": 1763, "delays": 352}, "US": {"flights": 64, "delays": 6}, "OO": {"flights": 562, "delays": 121}, "UA": {"flights": 3, "delays": 0}, "AA": {"flights": 141, "delays": 10}, "AS": {"flights": 26, "delays": 2}}}, {"name_iata": "CID", "name": "The Eastern Iowa Airport", "airlines": {"EV": {"flights": 1902, "delays": 271}, "OO": {"flights": 2026, "delays": 360}, "MQ": {"flights": 2579, "delays": 492}, "F9": {"flights": 101, "delays": 19}}}, {"name_iata": "CIU", "name": "Chippewa County International Airport", "airlines": {"OO": {"flights": 597, "delays": 86}}}, {"name_iata": "CLD", "name": "McClellan-Palomar Airport", "airlines": {"OO": {"flights": 628, "delays": 71}}}, {"name_iata": "CLE", "name": "Cleveland Hopkins International Airport", "airlines": {"UA": {"flights": 6465, "delays": 965}, "F9": {"flights": 2985, "delays": 660}, "EV": {"flights": 9986, "delays": 1486}, "AA": {"flights": 1767, "delays": 246}, "US": {"flights": 911, "delays": 75}, "WN": {"flights": 4378, "delays": 613}, "DL": {"flights": 2278, "delays": 189}, "OO": {"flights": 458, "delays": 89}, "MQ": {"flights": 1875, "delays": 420}, "NK": {"flights": 2124, "delays": 503}, "B6": {"flights": 628, "delays": 82}}}, {"name_iata": "CLL", "name": "Easterwood Airport", "airlines": {"MQ": {"flights": 1510, "delays": 189}, "EV": {"flights": 692, "delays": 54}}}, {"name_iata": "CLT", "name": "Charlotte Douglas International Airport", "airlines": {"EV": {"flights": 3323, "delays": 659}, "AA": {"flights": 41518, "delays": 6855}, "US": {"flights": 43778, "delays": 7085}, "DL": {"flights": 5979, "delays": 723}, "WN": {"flights": 1760, "delays": 413}, "B6": {"flights": 1240, "delays": 320}, "UA": {"flights": 269, "delays": 55}, "F9": {"flights": 553, "delays": 148}, "OO": {"flights": 708, "delays": 193}, "MQ": {"flights": 115, "delays": 19}}}, {"name_iata": "CMH", "name": "Port Columbus International Airport", "airlines": {"MQ": {"flights": 4362, "delays": 946}, "WN": {"flights": 9915, "delays": 1620}, "AA": {"flights": 1884, "delays": 227}, "DL": {"flights": 3031, "delays": 364}, "US": {"flights": 493, "delays": 73}, "UA": {"flights": 692, "delays": 129}, "EV": {"flights": 2397, "delays": 511}, "OO": {"flights": 875, "delays": 173}}}, {"name_iata": "CMI", "name": "University of Illinois - Willard Airport", "airlines": {"MQ": {"flights": 1999, "delays": 276}}}, {"name_iata": "CMX", "name": "Houghton County Memorial Airport", "airlines": {"OO": {"flights": 623, "delays": 73}}}, {"name_iata": "CNY", "name": "Canyonlands Field", "airlines": {"OO": {"flights": 205, "delays": 6}}}, {"name_iata": "COD", "name": "Yellowstone Regional Airport", "airlines": {"OO": {"flights": 653, "delays": 97}}}, {"name_iata": "COS", "name": "City of Colorado Springs Municipal Airport", "airlines": {"OO": {"flights": 4909, "delays": 765}, "DL": {"flights": 305, "delays": 34}, "AA": {"flights": 1056, "delays": 126}, "EV": {"flights": 495, "delays": 70}}}, {"name_iata": "COU", "name": "Columbia Regional Airport", "airlines": {"MQ": {"flights": 1244, "delays": 221}}}, {"name_iata": "CPR", "name": "Natrona County International Airport", "airlines": {"OO": {"flights": 1745, "delays": 168}}}, {"name_iata": "CRP", "name": "Corpus Christi International Airport", "airlines": {"EV": {"flights": 2569, "delays": 440}, "WN": {"flights": 1240, "delays": 176}, "MQ": {"flights": 733, "delays": 155}, "OO": {"flights": 195, "delays": 19}}}, {"name_iata": "CRW", "name": "Yeager Airport", "airlines": {"EV": {"flights": 1909, "delays": 383}, "DL": {"flights": 314, "delays": 29}, "NK": {"flights": 64, "delays": 12}, "OO": {"flights": 39, "delays": 9}}}, {"name_iata": "CSG", "name": "Columbus Metropolitan Airport", "airlines": {"EV": {"flights": 1061, "delays": 141}}}, {"name_iata": "CVG", "name": "Cincinnati/Northern Kentucky International Airport", "airlines": {"MQ": {"flights": 4653, "delays": 815}, "DL": {"flights": 5802, "delays": 565}, "F9": {"flights": 2020, "delays": 494}, "EV": {"flights": 3007, "delays": 508}, "OO": {"flights": 4038, "delays": 778}, "UA": {"flights": 3, "delays": 1}}}, {"name_iata": "CWA", "name": "Central Wisconsin Airport", "airlines": {"EV": {"flights": 599, "delays": 84}, "MQ": {"flights": 705, "delays": 76}, "OO": {"flights": 60, "delays": 9}}}, {"name_iata": "DAB", "name": "Daytona Beach International Airport", "airlines": {"DL": {"flights": 1483, "delays": 167}, "US": {"flights": 5, "delays": 0}, "EV": {"flights": 2, "delays": 1}}}, {"name_iata": "DAL", "name": "Dallas Love Field", "airlines": {"OO": {"flights": 5, "delays": 3}, "WN": {"flights": 51934, "delays": 12174}, "DL": {"flights": 1424, "delays": 183}, "VX": {"flights": 4967, "delays": 1004}, "EV": {"flights": 519, "delays": 55}}}, {"name_iata": "DAY", "name": "James M. Cox Dayton International Airport", "airlines": {"AA": {"flights": 907, "delays": 119}, "MQ": {"flights": 1552, "delays": 272}, "EV": {"flights": 1716, "delays": 302}, "WN": {"flights": 1473, "delays": 200}, "DL": {"flights": 1310, "delays": 160}, "OO": {"flights": 1427, "delays": 224}}}, {"name_iata": "DBQ", "name": "Dubuque Regional Airport", "airlines": {"MQ": {"flights": 870, "delays": 114}}}, {"name_iata": "DCA", "name": "Ronald Reagan Washington National Airport", "airlines": {"UA": {"flights": 4527, "delays": 893}, "B6": {"flights": 9355, "delays": 1483}, "AA": {"flights": 17492, "delays": 2686}, "DL": {"flights": 8518, "delays": 1200}, "MQ": {"flights": 643, "delays": 192}, "US": {"flights": 9672, "delays": 1493}, "WN": {"flights": 13784, "delays": 1985}, "F9": {"flights": 985, "delays": 140}, "OO": {"flights": 1461, "delays": 263}, "AS": {"flights": 1323, "delays": 123}, "EV": {"flights": 2793, "delays": 463}, "VX": {"flights": 1214, "delays": 176}}}, {"name_iata": "DEN", "name": "Denver International Airport", "airlines": {"DL": {"flights": 7054, "delays": 1078}, "AA": {"flights": 6997, "delays": 1220}, "OO": {"flights": 43908, "delays": 9150}, "US": {"flights": 2305, "delays": 285}, "UA": {"flights": 45757, "delays": 11520}, "AS": {"flights": 1586, "delays": 140}, "WN": {"flights": 55276, "delays": 12829}, "F9": {"flights": 21124, "delays": 4074}, "EV": {"flights": 5369, "delays": 1112}, "NK": {"flights": 3614, "delays": 940}, "B6": {"flights": 942, "delays": 280}}}, {"name_iata": "DFW", "name": "Dallas/Fort Worth International Airport", "airlines": {"AA": {"flights": 131508, "delays": 27957}, "DL": {"flights": 5080, "delays": 734}, "NK": {"flights": 8392, "delays": 1969}, "OO": {"flights": 4035, "delays": 859}, "US": {"flights": 3018, "delays": 406}, "F9": {"flights": 1283, "delays": 287}, "UA": {"flights": 3449, "delays": 682}, "MQ": {"flights": 51214, "delays": 10977}, "AS": {"flights": 1345, "delays": 149}, "EV": {"flights": 23392, "delays": 5429}, "B6": {"flights": 581, "delays": 153}}}, {"name_iata": "DHN", "name": "Dothan Regional Airport", "airlines": {"EV": {"flights": 1243, "delays": 190}}}, {"name_iata": "DIK", "name": "Dickinson Theodore Roosevelt Regional Airport", "airlines": {"EV": {"flights": 332, "delays": 45}, "OO": {"flights": 589, "delays": 28}}}, {"name_iata": "DLG", "name": "Dillingham Airport", "airlines": {"AS": {"flights": 77, "delays": 11}}}, {"name_iata": "DLH", "name": "Duluth International Airport", "airlines": {"OO": {"flights": 1468, "delays": 233}, "DL": {"flights": 199, "delays": 23}}}, {"name_iata": "DRO", "name": "Durango-La Plata County Airport", "airlines": {"OO": {"flights": 1156, "delays": 132}, "MQ": {"flights": 785, "delays": 153}, "EV": {"flights": 83, "delays": 12}}}, {"name_iata": "DSM", "name": "Des Moines International Airport", "airlines": {"AA": {"flights": 792, "delays": 114}, "MQ": {"flights": 2026, "delays": 406}, "WN": {"flights": 964, "delays": 145}, "OO": {"flights": 1342, "delays": 255}, "EV": {"flights": 1213, "delays": 222}, "UA": {"flights": 685, "delays": 141}, "F9": {"flights": 173, "delays": 29}, "US": {"flights": 1, "delays": 0}, "DL": {"flights": 934, "delays": 108}}}, {"name_iata": "DTW", "name": "Detroit Metropolitan Airport", "airlines": {"NK": {"flights": 7181, "delays": 1976}, "US": {"flights": 1539, "delays": 171}, "B6": {"flights": 1173, "delays": 168}, "MQ": {"flights": 2151, "delays": 570}, "DL": {"flights": 50370, "delays": 7445}, "WN": {"flights": 6189, "delays": 1072}, "OO": {"flights": 10253, "delays": 1525}, "UA": {"flights": 935, "delays": 178}, "AA": {"flights": 3987, "delays": 509}, "EV": {"flights": 22478, "delays": 3700}, "AS": {"flights": 335, "delays": 39}, "F9": {"flights": 639, "delays": 115}}}, {"name_iata": "DVL", "name": "Devils Lake Regional Airport", "airlines": {"OO": {"flights": 479, "delays": 61}}}, {"name_iata": "EAU", "name": "Chippewa Valley Regional Airport", "airlines": {"OO": {"flights": 635, "delays": 95}}}, {"name_iata": "ECP", "name": "Northwest Florida Beaches International Airport", "airlines": {"WN": {"flights": 1603, "delays": 213}, "EV": {"flights": 666, "delays": 73}, "DL": {"flights": 1880, "delays": 216}}}, {"name_iata": "EGE", "name": "Eagle County Regional Airport", "airlines": {"AA": {"flights": 854, "delays": 161}, "DL": {"flights": 101, "delays": 23}, "UA": {"flights": 249, "delays": 77}}}, {"name_iata": "EKO", "name": "Elko Regional Airport", "airlines": {"OO": {"flights": 517, "delays": 26}}}, {"name_iata": "ELM", "name": "Elmira/Corning Regional Airport", "airlines": {"EV": {"flights": 2011, "delays": 273}}}, {"name_iata": "ELP", "name": "El Paso International Airport", "airlines": {"AA": {"flights": 1333, "delays": 198}, "EV": {"flights": 1520, "delays": 161}, "WN": {"flights": 6325, "delays": 1091}, "OO": {"flights": 1410, "delays": 189}, "DL": {"flights": 698, "delays": 90}, "MQ": {"flights": 554, "delays": 109}}}, {"name_iata": "ERI", "name": "Erie International Airport", "airlines": {"EV": {"flights": 710, "delays": 96}}}, {"name_iata": "ESC", "name": "Delta County Airport", "airlines": {"OO": {"flights": 556, "delays": 53}}}, {"name_iata": "EUG", "name": "Eugene Airport\u00a0(Mahlon Sweet Field)", "airlines": {"OO": {"flights": 3565, "delays": 537}}}, {"name_iata": "EVV", "name": "Evansville Regional Airport", "airlines": {"EV": {"flights": 1811, "delays": 269}, "MQ": {"flights": 1503, "delays": 246}, "DL": {"flights": 354, "delays": 24}, "OO": {"flights": 46, "delays": 6}}}, {"name_iata": "EWN", "name": "Coastal Carolina Regional Airport\u00a0(Craven County Regional)", "airlines": {"EV": {"flights": 567, "delays": 70}}}, {"name_iata": "EWR", "name": "Newark Liberty International Airport", "airlines": {"AA": {"flights": 5291, "delays": 793}, "UA": {"flights": 42296, "delays": 12341}, "B6": {"flights": 6220, "delays": 1235}, "US": {"flights": 2015, "delays": 239}, "DL": {"flights": 4956, "delays": 711}, "EV": {"flights": 29781, "delays": 5920}, "AS": {"flights": 652, "delays": 71}, "WN": {"flights": 5275, "delays": 1069}, "VX": {"flights": 1812, "delays": 246}, "OO": {"flights": 2, "delays": 1}, "MQ": {"flights": 362, "delays": 90}}}, {"name_iata": "EYW", "name": "Key West International Airport", "airlines": {"EV": {"flights": 428, "delays": 59}, "MQ": {"flights": 536, "delays": 89}, "DL": {"flights": 990, "delays": 100}}}, {"name_iata": "FAI", "name": "Fairbanks International Airport", "airlines": {"AS": {"flights": 1868, "delays": 171}, "DL": {"flights": 232, "delays": 39}, "UA": {"flights": 73, "delays": 54}}}, {"name_iata": "FAR", "name": "Hector International Airport", "airlines": {"EV": {"flights": 1314, "delays": 218}, "OO": {"flights": 2229, "delays": 316}, "MQ": {"flights": 1273, "delays": 195}, "F9": {"flights": 54, "delays": 20}, "DL": {"flights": 712, "delays": 55}}}, {"name_iata": "FAT", "name": "Fresno Yosemite International Airport", "airlines": {"OO": {"flights": 6338, "delays": 1049}, "AA": {"flights": 611, "delays": 112}, "F9": {"flights": 2, "delays": 1}}}, {"name_iata": "FAY", "name": "Fayetteville Regional Airport", "airlines": {"EV": {"flights": 1148, "delays": 207}, "DL": {"flights": 470, "delays": 42}}}, {"name_iata": "FCA", "name": "Glacier Park International Airport", "airlines": {"OO": {"flights": 1714, "delays": 170}, "DL": {"flights": 292, "delays": 22}}}, {"name_iata": "FLG", "name": "Flagstaff Pulliam Airport", "airlines": {"OO": {"flights": 1610, "delays": 175}}}, {"name_iata": "FLL", "name": "Fort Lauderdale-Hollywood International Airport", "airlines": {"B6": {"flights": 17744, "delays": 4677}, "UA": {"flights": 5082, "delays": 888}, "US": {"flights": 3077, "delays": 396}, "WN": {"flights": 17510, "delays": 3155}, "DL": {"flights": 10507, "delays": 1432}, "NK": {"flights": 11399, "delays": 2675}, "AA": {"flights": 5250, "delays": 646}, "VX": {"flights": 1232, "delays": 250}, "F9": {"flights": 695, "delays": 197}, "AS": {"flights": 334, "delays": 70}}}, {"name_iata": "FNT", "name": "Bishop International Airport", "airlines": {"MQ": {"flights": 903, "delays": 118}, "EV": {"flights": 896, "delays": 103}, "DL": {"flights": 927, "delays": 82}, "WN": {"flights": 1473, "delays": 189}, "OO": {"flights": 438, "delays": 30}}}, {"name_iata": "FSD", "name": "Sioux Falls Regional Airport", "airlines": {"OO": {"flights": 1982, "delays": 331}, "EV": {"flights": 1724, "delays": 266}, "MQ": {"flights": 874, "delays": 183}, "F9": {"flights": 168, "delays": 48}, "DL": {"flights": 425, "delays": 25}, "UA": {"flights": 4, "delays": 0}}}, {"name_iata": "FSM", "name": "Fort Smith Regional Airport", "airlines": {"MQ": {"flights": 512, "delays": 88}, "EV": {"flights": 1401, "delays": 196}}}, {"name_iata": "FWA", "name": "Fort Wayne International Airport", "airlines": {"MQ": {"flights": 1815, "delays": 279}, "OO": {"flights": 2950, "delays": 461}, "EV": {"flights": 325, "delays": 52}}}, {"name_iata": "GCC", "name": "Gillette-Campbell County Airport", "airlines": {"OO": {"flights": 986, "delays": 94}}}, {"name_iata": "GCK", "name": "Garden City Regional Airport", "airlines": {"MQ": {"flights": 613, "delays": 69}, "EV": {"flights": 25, "delays": 10}}}, {"name_iata": "GEG", "name": "Spokane International Airport", "airlines": {"AS": {"flights": 1528, "delays": 154}, "UA": {"flights": 617, "delays": 85}, "WN": {"flights": 2905, "delays": 412}, "F9": {"flights": 5, "delays": 1}, "US": {"flights": 322, "delays": 23}, "DL": {"flights": 1440, "delays": 142}, "OO": {"flights": 2377, "delays": 288}, "AA": {"flights": 262, "delays": 18}}}, {"name_iata": "GFK", "name": "Grand Forks International Airport", "airlines": {"OO": {"flights": 714, "delays": 77}}}, {"name_iata": "GGG", "name": "East Texas Regional Airport", "airlines": {"EV": {"flights": 147, "delays": 39}, "MQ": {"flights": 468, "delays": 65}}}, {"name_iata": "GJT", "name": "Grand Junction Regional Airport\u00a0(Walker Field)", "airlines": {"OO": {"flights": 1974, "delays": 158}, "EV": {"flights": 337, "delays": 40}, "MQ": {"flights": 829, "delays": 109}}}, {"name_iata": "GNV", "name": "Gainesville Regional Airport", "airlines": {"MQ": {"flights": 571, "delays": 87}, "EV": {"flights": 1802, "delays": 313}, "DL": {"flights": 271, "delays": 22}}}, {"name_iata": "GPT", "name": "Gulfport-Biloxi International Airport", "airlines": {"EV": {"flights": 1981, "delays": 246}, "DL": {"flights": 1132, "delays": 121}, "MQ": {"flights": 416, "delays": 72}}}, {"name_iata": "GRB", "name": "Green Bay-Austin Straubel International Airport", "airlines": {"EV": {"flights": 1732, "delays": 198}, "MQ": {"flights": 1219, "delays": 164}, "OO": {"flights": 1163, "delays": 153}, "DL": {"flights": 616, "delays": 51}}}, {"name_iata": "GRI", "name": "Central Nebraska Regional Airport", "airlines": {"MQ": {"flights": 611, "delays": 70}}}, {"name_iata": "GRK", "name": "Killeen-Fort Hood Regional Airport", "airlines": {"MQ": {"flights": 1353, "delays": 198}, "EV": {"flights": 2524, "delays": 353}}}, {"name_iata": "GRR", "name": "Gerald R. Ford International Airport", "airlines": {"WN": {"flights": 1837, "delays": 243}, "MQ": {"flights": 2604, "delays": 514}, "OO": {"flights": 1125, "delays": 177}, "EV": {"flights": 1644, "delays": 278}, "DL": {"flights": 2822, "delays": 253}, "UA": {"flights": 537, "delays": 106}}}, {"name_iata": "GSO", "name": "Piedmont Triad International Airport", "airlines": {"EV": {"flights": 3135, "delays": 639}, "MQ": {"flights": 1177, "delays": 248}, "DL": {"flights": 1891, "delays": 175}, "F9": {"flights": 133, "delays": 27}, "US": {"flights": 1, "delays": 0}, "AA": {"flights": 141, "delays": 14}, "OO": {"flights": 3, "delays": 1}}}, {"name_iata": "GSP", "name": "Greenville-Spartanburg International Airport", "airlines": {"DL": {"flights": 1673, "delays": 176}, "WN": {"flights": 1306, "delays": 263}, "EV": {"flights": 2937, "delays": 416}, "MQ": {"flights": 465, "delays": 74}, "OO": {"flights": 23, "delays": 2}}}, {"name_iata": "GST", "name": "Gustavus Airport", "airlines": {"AS": {"flights": 76, "delays": 29}}}, {"name_iata": "GTF", "name": "Great Falls International Airport", "airlines": {"OO": {"flights": 1952, "delays": 132}}}, {"name_iata": "GTR", "name": "Golden Triangle Regional Airport", "airlines": {"EV": {"flights": 913, "delays": 112}}}, {"name_iata": "GUC", "name": "Gunnison-Crested Butte Regional Airport", "airlines": {"EV": {"flights": 156, "delays": 25}, "UA": {"flights": 24, "delays": 7}, "AA": {"flights": 113, "delays": 15}, "MQ": {"flights": 8, "delays": 2}, "OO": {"flights": 171, "delays": 39}}}, {"name_iata": "GUM", "name": "Guam International Airport", "airlines": {"UA": {"flights": 331, "delays": 86}}}, {"name_iata": "HDN", "name": "Yampa Valley Airport\u00a0(Yampa Valley Regional)", "airlines": {"EV": {"flights": 72, "delays": 6}, "AA": {"flights": 133, "delays": 21}, "DL": {"flights": 95, "delays": 23}, "UA": {"flights": 151, "delays": 36}, "OO": {"flights": 236, "delays": 58}}}, {"name_iata": "HIB", "name": "Range Regional Airport\u00a0(Chisholm-Hibbing Airport)", "airlines": {"OO": {"flights": 878, "delays": 81}}}, {"name_iata": "HLN", "name": "Helena Regional Airport", "airlines": {"OO": {"flights": 1426, "delays": 79}}}, {"name_iata": "HNL", "name": "Honolulu International Airport", "airlines": {"HA": {"flights": 30157, "delays": 1894}, "UA": {"flights": 4876, "delays": 832}, "DL": {"flights": 2751, "delays": 293}, "AA": {"flights": 2385, "delays": 327}, "AS": {"flights": 2351, "delays": 250}, "US": {"flights": 419, "delays": 50}, "VX": {"flights": 59, "delays": 4}}}, {"name_iata": "HOB", "name": "Lea County Regional Airport", "airlines": {"EV": {"flights": 548, "delays": 48}}}, {"name_iata": "HOU", "name": "William P. Hobby Airport", "airlines": {"WN": {"flights": 46978, "delays": 10858}, "MQ": {"flights": 1173, "delays": 215}, "DL": {"flights": 1697, "delays": 203}, "B6": {"flights": 659, "delays": 213}, "AA": {"flights": 160, "delays": 18}, "EV": {"flights": 601, "delays": 135}}}, {"name_iata": "HPN", "name": "Westchester County Airport", "airlines": {"B6": {"flights": 3532, "delays": 707}, "MQ": {"flights": 890, "delays": 161}, "EV": {"flights": 2742, "delays": 591}}}, {"name_iata": "HRL", "name": "Valley International Airport", "airlines": {"WN": {"flights": 1860, "delays": 227}, "EV": {"flights": 1144, "delays": 96}, "OO": {"flights": 32, "delays": 3}}}, {"name_iata": "HSV", "name": "Huntsville International Airport", "airlines": {"DL": {"flights": 1758, "delays": 179}, "MQ": {"flights": 645, "delays": 141}, "EV": {"flights": 2033, "delays": 290}}}, {"name_iata": "HYA", "name": "Barnstable Municipal Airport", "airlines": {"B6": {"flights": 82, "delays": 18}}}, {"name_iata": "HYS", "name": "Hays Regional Airport", "airlines": {"OO": {"flights": 558, "delays": 75}}}, {"name_iata": "IAD", "name": "Washington Dulles International Airport", "airlines": {"UA": {"flights": 17851, "delays": 4040}, "F9": {"flights": 1921, "delays": 445}, "AA": {"flights": 2461, "delays": 415}, "B6": {"flights": 1832, "delays": 313}, "EV": {"flights": 3179, "delays": 689}, "VX": {"flights": 1480, "delays": 176}, "WN": {"flights": 2168, "delays": 313}, "DL": {"flights": 2355, "delays": 295}, "OO": {"flights": 239, "delays": 38}, "AS": {"flights": 264, "delays": 34}}}, {"name_iata": "IAG", "name": "Niagara Falls International Airport", "airlines": {"NK": {"flights": 312, "delays": 49}}}, {"name_iata": "IAH", "name": "George Bush Intercontinental Airport", "airlines": {"AA": {"flights": 6387, "delays": 870}, "US": {"flights": 2432, "delays": 299}, "F9": {"flights": 1522, "delays": 364}, "NK": {"flights": 5002, "delays": 1720}, "UA": {"flights": 53391, "delays": 14852}, "EV": {"flights": 57299, "delays": 7504}, "DL": {"flights": 2923, "delays": 461}, "OO": {"flights": 15132, "delays": 3481}, "AS": {"flights": 379, "delays": 49}, "MQ": {"flights": 25, "delays": 6}}}, {"name_iata": "ICT", "name": "Wichita Dwight D. Eisenhower National Airport\u00a0(Wichita Mid-Continent Airport)", "airlines": {"OO": {"flights": 2438, "delays": 498}, "DL": {"flights": 857, "delays": 101}, "AA": {"flights": 164, "delays": 23}, "WN": {"flights": 1519, "delays": 231}, "UA": {"flights": 456, "delays": 81}, "EV": {"flights": 2087, "delays": 327}, "MQ": {"flights": 380, "delays": 93}}}, {"name_iata": "IDA", "name": "Idaho Falls Regional Airport", "airlines": {"OO": {"flights": 2226, "delays": 180}, "F9": {"flights": 2, "delays": 0}}}, {"name_iata": "ILG", "name": "Wilmington Airport", "airlines": {"F9": {"flights": 95, "delays": 35}}}, {"name_iata": "ILM", "name": "Wilmington International Airport", "airlines": {"EV": {"flights": 1321, "delays": 173}, "US": {"flights": 1, "delays": 0}, "DL": {"flights": 347, "delays": 32}, "AA": {"flights": 160, "delays": 11}, "OO": {"flights": 15, "delays": 2}}}, {"name_iata": "IMT", "name": "Ford Airport", "airlines": {"OO": {"flights": 609, "delays": 49}}}, {"name_iata": "IND", "name": "Indianapolis International Airport", "airlines": {"US": {"flights": 875, "delays": 86}, "F9": {"flights": 731, "delays": 132}, "AA": {"flights": 2733, "delays": 355}, "DL": {"flights": 4391, "delays": 542}, "WN": {"flights": 10077, "delays": 1601}, "UA": {"flights": 1102, "delays": 187}, "EV": {"flights": 2888, "delays": 535}, "OO": {"flights": 422, "delays": 101}, "MQ": {"flights": 1898, "delays": 340}}}, {"name_iata": "INL", "name": "Falls International Airport", "airlines": {"OO": {"flights": 565, "delays": 55}}}, {"name_iata": "ISN", "name": "Sloulin Field International Airport", "airlines": {"EV": {"flights": 550, "delays": 81}, "OO": {"flights": 1963, "delays": 211}}}, {"name_iata": "ISP", "name": "Long Island MacArthur Airport", "airlines": {"WN": {"flights": 4257, "delays": 756}}}, {"name_iata": "ITH", "name": "Ithaca Tompkins Regional Airport", "airlines": {"EV": {"flights": 10, "delays": 1}, "OO": {"flights": 20, "delays": 6}}}, {"name_iata": "ITO", "name": "Hilo International Airport", "airlines": {"HA": {"flights": 5453, "delays": 321}, "UA": {"flights": 258, "delays": 47}}}, {"name_iata": "JAC", "name": "Jackson Hole Airport", "airlines": {"UA": {"flights": 1001, "delays": 210}, "AA": {"flights": 409, "delays": 55}, "DL": {"flights": 769, "delays": 69}, "OO": {"flights": 1278, "delays": 187}}}, {"name_iata": "JAN", "name": "Jackson-Evers International Airport", "airlines": {"EV": {"flights": 3853, "delays": 522}, "DL": {"flights": 1895, "delays": 203}, "MQ": {"flights": 1179, "delays": 275}}}, {"name_iata": "JAX", "name": "Jacksonville International Airport", "airlines": {"EV": {"flights": 1948, "delays": 411}, "B6": {"flights": 2969, "delays": 554}, "AA": {"flights": 2332, "delays": 336}, "US": {"flights": 1354, "delays": 169}, "DL": {"flights": 4224, "delays": 483}, "WN": {"flights": 4236, "delays": 699}, "MQ": {"flights": 487, "delays": 96}, "OO": {"flights": 209, "delays": 72}, "UA": {"flights": 68, "delays": 16}}}, {"name_iata": "JFK", "name": "John F. Kennedy International Airport\u00a0(New York International Airport)", "airlines": {"B6": {"flights": 39684, "delays": 8301}, "AA": {"flights": 15282, "delays": 2729}, "DL": {"flights": 25091, "delays": 5493}, "UA": {"flights": 3239, "delays": 455}, "US": {"flights": 1362, "delays": 306}, "VX": {"flights": 3620, "delays": 444}, "MQ": {"flights": 3243, "delays": 770}, "HA": {"flights": 293, "delays": 19}, "AS": {"flights": 75, "delays": 7}}}, {"name_iata": "JLN", "name": "Joplin Regional Airport", "airlines": {"MQ": {"flights": 347, "delays": 75}, "EV": {"flights": 286, "delays": 30}}}, {"name_iata": "JMS", "name": "Jamestown Regional Airport", "airlines": {"OO": {"flights": 753, "delays": 120}}}, {"name_iata": "JNU", "name": "Juneau International Airport", "airlines": {"AS": {"flights": 3854, "delays": 521}, "DL": {"flights": 139, "delays": 26}, "OO": {"flights": 52, "delays": 15}}}, {"name_iata": "KOA", "name": "Kona International Airport at Keahole", "airlines": {"HA": {"flights": 7281, "delays": 482}, "AS": {"flights": 1389, "delays": 121}, "AA": {"flights": 597, "delays": 74}, "UA": {"flights": 1280, "delays": 212}, "US": {"flights": 181, "delays": 9}, "DL": {"flights": 346, "delays": 48}}}, {"name_iata": "KTN", "name": "Ketchikan International Airport", "airlines": {"AS": {"flights": 2177, "delays": 301}, "OO": {"flights": 114, "delays": 34}}}, {"name_iata": "LAN", "name": "Capital Region International Airport\u00a0( Lansing Capital City)", "airlines": {"EV": {"flights": 1029, "delays": 128}, "OO": {"flights": 769, "delays": 111}, "DL": {"flights": 4, "delays": 0}}}, {"name_iata": "LAR", "name": "Laramie Regional Airport", "airlines": {"OO": {"flights": 557, "delays": 53}}}, {"name_iata": "LAS", "name": "McCarran International Airport", "airlines": {"NK": {"flights": 8904, "delays": 2355}, "DL": {"flights": 10601, "delays": 1196}, "AA": {"flights": 11253, "delays": 1459}, "US": {"flights": 2991, "delays": 252}, "HA": {"flights": 811, "delays": 69}, "WN": {"flights": 68110, "delays": 16763}, "UA": {"flights": 11052, "delays": 1929}, "F9": {"flights": 4309, "delays": 1046}, "AS": {"flights": 4066, "delays": 367}, "VX": {"flights": 3732, "delays": 796}, "B6": {"flights": 4019, "delays": 985}, "OO": {"flights": 2397, "delays": 345}}}, {"name_iata": "LAW", "name": "Lawton-Fort Sill Regional Airport", "airlines": {"EV": {"flights": 632, "delays": 77}, "MQ": {"flights": 605, "delays": 114}}}, {"name_iata": "LAX", "name": "Los Angeles International Airport", "airlines": {"AA": {"flights": 32415, "delays": 4629}, "US": {"flights": 3661, "delays": 452}, "DL": {"flights": 25117, "delays": 4818}, "UA": {"flights": 27131, "delays": 5945}, "AS": {"flights": 8048, "delays": 743}, "B6": {"flights": 4075, "delays": 877}, "NK": {"flights": 4289, "delays": 1426}, "OO": {"flights": 36236, "delays": 7093}, "WN": {"flights": 36715, "delays": 10703}, "VX": {"flights": 11725, "delays": 2114}, "HA": {"flights": 1550, "delays": 119}, "MQ": {"flights": 171, "delays": 36}, "F9": {"flights": 1376, "delays": 299}}}, {"name_iata": "LBB", "name": "Lubbock Preston Smith International Airport", "airlines": {"EV": {"flights": 1293, "delays": 175}, "MQ": {"flights": 375, "delays": 103}, "WN": {"flights": 2180, "delays": 265}, "AA": {"flights": 294, "delays": 40}, "OO": {"flights": 333, "delays": 65}}}, {"name_iata": "LBE", "name": "Arnold Palmer Regional Airport", "airlines": {"NK": {"flights": 1245, "delays": 269}}}, {"name_iata": "LCH", "name": "Lake Charles Regional Airport", "airlines": {"EV": {"flights": 1166, "delays": 112}, "MQ": {"flights": 638, "delays": 82}}}, {"name_iata": "LEX", "name": "Blue Grass Airport", "airlines": {"EV": {"flights": 3223, "delays": 470}, "MQ": {"flights": 1201, "delays": 187}, "DL": {"flights": 991, "delays": 67}, "OO": {"flights": 394, "delays": 55}}}, {"name_iata": "LFT", "name": "Lafayette Regional Airport", "airlines": {"EV": {"flights": 3426, "delays": 535}, "MQ": {"flights": 1154, "delays": 159}, "DL": {"flights": 341, "delays": 33}, "OO": {"flights": 102, "delays": 12}}}, {"name_iata": "LGA", "name": "LaGuardia Airport (Marine Air Terminal)", "airlines": {"AA": {"flights": 17466, "delays": 2599}, "B6": {"flights": 5978, "delays": 1602}, "DL": {"flights": 23807, "delays": 5174}, "NK": {"flights": 3497, "delays": 947}, "UA": {"flights": 7862, "delays": 1629}, "WN": {"flights": 9914, "delays": 2470}, "US": {"flights": 5892, "delays": 966}, "EV": {"flights": 9285, "delays": 2357}, "F9": {"flights": 852, "delays": 292}, "MQ": {"flights": 9261, "delays": 2568}, "VX": {"flights": 1162, "delays": 250}, "OO": {"flights": 98, "delays": 13}}}, {"name_iata": "LGB", "name": "Long Beach Airport\u00a0(Daugherty Field)", "airlines": {"B6": {"flights": 7471, "delays": 1342}, "OO": {"flights": 1246, "delays": 98}}}, {"name_iata": "LIH", "name": "Lihue Airport", "airlines": {"HA": {"flights": 7286, "delays": 474}, "AS": {"flights": 1194, "delays": 115}, "UA": {"flights": 825, "delays": 108}, "AA": {"flights": 680, "delays": 66}, "US": {"flights": 182, "delays": 7}, "DL": {"flights": 334, "delays": 46}}}, {"name_iata": "LIT", "name": "Bill and Hillary Clinton National Airport\u00a0(Adams Field)", "airlines": {"AA": {"flights": 9, "delays": 2}, "WN": {"flights": 2299, "delays": 387}, "DL": {"flights": 1924, "delays": 175}, "MQ": {"flights": 2301, "delays": 538}, "EV": {"flights": 2814, "delays": 441}, "OO": {"flights": 808, "delays": 151}}}, {"name_iata": "LNK", "name": "Lincoln Airport\u00a0(Lincoln Municipal)", "airlines": {"EV": {"flights": 1448, "delays": 157}, "OO": {"flights": 1120, "delays": 152}}}, {"name_iata": "LRD", "name": "Laredo International Airport", "airlines": {"EV": {"flights": 1245, "delays": 131}, "MQ": {"flights": 893, "delays": 120}}}, {"name_iata": "LSE", "name": "La Crosse Regional Airport", "airlines": {"MQ": {"flights": 1099, "delays": 145}, "OO": {"flights": 483, "delays": 39}}}, {"name_iata": "LWS", "name": "Lewiston-Nez Perce County Airport", "airlines": {"OO": {"flights": 588, "delays": 17}}}, {"name_iata": "MAF", "name": "Midland International Airport", "airlines": {"WN": {"flights": 3136, "delays": 480}, "OO": {"flights": 1290, "delays": 174}, "EV": {"flights": 1829, "delays": 248}, "MQ": {"flights": 1021, "delays": 239}}}, {"name_iata": "MBS", "name": "MBS International Airport", "airlines": {"OO": {"flights": 1508, "delays": 247}, "EV": {"flights": 146, "delays": 19}}}, {"name_iata": "MCI", "name": "Kansas City International Airport", "airlines": {"DL": {"flights": 5071, "delays": 526}, "US": {"flights": 1194, "delays": 113}, "EV": {"flights": 3248, "delays": 457}, "AA": {"flights": 3741, "delays": 542}, "F9": {"flights": 346, "delays": 50}, "NK": {"flights": 1400, "delays": 390}, "WN": {"flights": 20564, "delays": 3539}, "OO": {"flights": 1562, "delays": 304}, "AS": {"flights": 396, "delays": 40}, "UA": {"flights": 589, "delays": 122}, "MQ": {"flights": 111, "delays": 26}}}, {"name_iata": "MCO", "name": "Orlando International Airport", "airlines": {"AA": {"flights": 12929, "delays": 2265}, "B6": {"flights": 17768, "delays": 4382}, "UA": {"flights": 11164, "delays": 2487}, "US": {"flights": 4625, "delays": 549}, "DL": {"flights": 15331, "delays": 2271}, "WN": {"flights": 37559, "delays": 7470}, "F9": {"flights": 4917, "delays": 1375}, "NK": {"flights": 4502, "delays": 1191}, "VX": {"flights": 334, "delays": 61}, "AS": {"flights": 649, "delays": 111}, "EV": {"flights": 86, "delays": 24}}}, {"name_iata": "MDT", "name": "Harrisburg International Airport", "airlines": {"DL": {"flights": 923, "delays": 101}, "F9": {"flights": 87, "delays": 13}, "EV": {"flights": 754, "delays": 93}, "MQ": {"flights": 790, "delays": 142}, "US": {"flights": 75, "delays": 9}, "UA": {"flights": 526, "delays": 74}, "OO": {"flights": 15, "delays": 3}, "AA": {"flights": 49, "delays": 1}}}, {"name_iata": "MDW", "name": "Chicago Midway International Airport", "airlines": {"WN": {"flights": 74441, "delays": 18071}, "DL": {"flights": 2513, "delays": 347}, "F9": {"flights": 50, "delays": 21}, "EV": {"flights": 1572, "delays": 318}, "OO": {"flights": 351, "delays": 61}}}, {"name_iata": "MEI", "name": "Meridian Regional Airport", "airlines": {"EV": {"flights": 893, "delays": 167}}}, {"name_iata": "MEM", "name": "Memphis International Airport", "airlines": {"DL": {"flights": 4069, "delays": 478}, "EV": {"flights": 3369, "delays": 603}, "AA": {"flights": 982, "delays": 153}, "US": {"flights": 429, "delays": 44}, "MQ": {"flights": 1249, "delays": 227}, "WN": {"flights": 2783, "delays": 520}, "F9": {"flights": 363, "delays": 67}, "OO": {"flights": 1074, "delays": 204}, "UA": {"flights": 107, "delays": 23}}}, {"name_iata": "MFE", "name": "McAllen-Miller International Airport\u00a0(McAllen Miller International)", "airlines": {"EV": {"flights": 1227, "delays": 145}, "AA": {"flights": 1404, "delays": 203}, "OO": {"flights": 405, "delays": 84}, "UA": {"flights": 264, "delays": 40}}}, {"name_iata": "MFR", "name": "Rogue Valley International Airport", "airlines": {"OO": {"flights": 2437, "delays": 372}}}, {"name_iata": "MGM", "name": "Montgomery Regional Airport", "airlines": {"EV": {"flights": 2271, "delays": 391}, "MQ": {"flights": 831, "delays": 132}, "OO": {"flights": 15, "delays": 3}}}, {"name_iata": "MHK", "name": "Manhattan Regional Airport", "airlines": {"MQ": {"flights": 1501, "delays": 172}, "EV": {"flights": 65, "delays": 13}}}, {"name_iata": "MHT", "name": "Manchester-Boston Regional Airport", "airlines": {"EV": {"flights": 1528, "delays": 242}, "WN": {"flights": 4170, "delays": 598}, "DL": {"flights": 443, "delays": 22}}}, {"name_iata": "MIA", "name": "Miami International Airport", "airlines": {"AA": {"flights": 47832, "delays": 11382}, "F9": {"flights": 2015, "delays": 610}, "UA": {"flights": 3112, "delays": 726}, "DL": {"flights": 8444, "delays": 1544}, "US": {"flights": 1759, "delays": 290}, "MQ": {"flights": 5216, "delays": 875}, "OO": {"flights": 180, "delays": 38}}}, {"name_iata": "MKE", "name": "General Mitchell International Airport", "airlines": {"EV": {"flights": 2568, "delays": 397}, "OO": {"flights": 7093, "delays": 1282}, "F9": {"flights": 601, "delays": 116}, "AA": {"flights": 1217, "delays": 162}, "WN": {"flights": 12735, "delays": 1997}, "DL": {"flights": 4646, "delays": 520}, "US": {"flights": 346, "delays": 28}, "MQ": {"flights": 42, "delays": 11}}}, {"name_iata": "MKG", "name": "Muskegon County Airport", "airlines": {"OO": {"flights": 618, "delays": 120}}}, {"name_iata": "MLB", "name": "Melbourne International Airport", "airlines": {"DL": {"flights": 1259, "delays": 147}, "EV": {"flights": 68, "delays": 27}}}, {"name_iata": "MLI", "name": "Quad City International Airport", "airlines": {"OO": {"flights": 476, "delays": 70}, "MQ": {"flights": 1682, "delays": 257}, "EV": {"flights": 1472, "delays": 271}}}, {"name_iata": "MLU", "name": "Monroe Regional Airport", "airlines": {"EV": {"flights": 2841, "delays": 411}, "MQ": {"flights": 43, "delays": 14}, "OO": {"flights": 4, "delays": 0}}}, {"name_iata": "MMH", "name": "Mammoth Yosemite Airport", "airlines": {"OO": {"flights": 140, "delays": 37}}}, {"name_iata": "MOB", "name": "Mobile Regional Airport", "airlines": {"DL": {"flights": 455, "delays": 30}, "EV": {"flights": 3559, "delays": 507}, "MQ": {"flights": 843, "delays": 170}, "OO": {"flights": 65, "delays": 12}}}, {"name_iata": "MOT", "name": "Minot International Airport", "airlines": {"OO": {"flights": 1630, "delays": 197}, "F9": {"flights": 3, "delays": 1}, "EV": {"flights": 186, "delays": 22}, "DL": {"flights": 4, "delays": 0}}}, {"name_iata": "MQT", "name": "Sawyer International Airport", "airlines": {"MQ": {"flights": 278, "delays": 41}, "OO": {"flights": 18, "delays": 4}}}, {"name_iata": "MRY", "name": "Monterey Regional Airport\u00a0(Monterey Peninsula Airport)", "airlines": {"OO": {"flights": 2840, "delays": 421}}}, {"name_iata": "MSN", "name": "Dane County Regional Airport", "airlines": {"F9": {"flights": 212, "delays": 29}, "OO": {"flights": 1411, "delays": 204}, "DL": {"flights": 2522, "delays": 206}, "MQ": {"flights": 2249, "delays": 318}, "EV": {"flights": 1950, "delays": 323}, "UA": {"flights": 507, "delays": 83}}}, {"name_iata": "MSO", "name": "Missoula International Airport", "airlines": {"OO": {"flights": 1372, "delays": 141}, "DL": {"flights": 597, "delays": 35}, "F9": {"flights": 89, "delays": 15}}}, {"name_iata": "MSP", "name": "Minneapolis-Saint Paul International Airport", "airlines": {"NK": {"flights": 3409, "delays": 1098}, "F9": {"flights": 1504, "delays": 311}, "UA": {"flights": 3162, "delays": 642}, "AA": {"flights": 5401, "delays": 770}, "DL": {"flights": 55833, "delays": 7058}, "OO": {"flights": 25330, "delays": 3188}, "US": {"flights": 2058, "delays": 261}, "WN": {"flights": 7188, "delays": 1274}, "AS": {"flights": 585, "delays": 58}, "EV": {"flights": 6672, "delays": 1427}, "MQ": {"flights": 167, "delays": 63}}}, {"name_iata": "MSY", "name": "Louis Armstrong New Orleans International Airport", "airlines": {"AA": {"flights": 3735, "delays": 491}, "B6": {"flights": 1107, "delays": 284}, "UA": {"flights": 4463, "delays": 776}, "DL": {"flights": 6927, "delays": 981}, "WN": {"flights": 17302, "delays": 2831}, "US": {"flights": 1083, "delays": 155}, "NK": {"flights": 1680, "delays": 425}, "EV": {"flights": 618, "delays": 78}, "F9": {"flights": 554, "delays": 158}, "AS": {"flights": 331, "delays": 42}, "OO": {"flights": 563, "delays": 87}, "MQ": {"flights": 30, "delays": 6}}}, {"name_iata": "MTJ", "name": "Montrose Regional Airport", "airlines": {"OO": {"flights": 622, "delays": 97}, "DL": {"flights": 35, "delays": 8}, "UA": {"flights": 73, "delays": 21}, "AA": {"flights": 29, "delays": 12}, "EV": {"flights": 151, "delays": 6}, "MQ": {"flights": 62, "delays": 9}}}, {"name_iata": "MVY", "name": "Martha's Vineyard Airport", "airlines": {"B6": {"flights": 205, "delays": 63}}}, {"name_iata": "MYR", "name": "Myrtle Beach International Airport", "airlines": {"NK": {"flights": 3164, "delays": 763}, "EV": {"flights": 712, "delays": 127}, "DL": {"flights": 851, "delays": 79}, "US": {"flights": 6, "delays": 1}}}, {"name_iata": "OAJ", "name": "Albert J. Ellis Airport", "airlines": {"EV": {"flights": 1121, "delays": 161}}}, {"name_iata": "OAK", "name": "Oakland International Airport", "airlines": {"US": {"flights": 295, "delays": 41}, "B6": {"flights": 1382, "delays": 224}, "NK": {"flights": 1584, "delays": 268}, "AS": {"flights": 2178, "delays": 146}, "OO": {"flights": 2210, "delays": 342}, "WN": {"flights": 32110, "delays": 7204}, "HA": {"flights": 766, "delays": 58}, "DL": {"flights": 919, "delays": 66}, "AA": {"flights": 299, "delays": 28}}}, {"name_iata": "OGG", "name": "Kahului Airport", "airlines": {"HA": {"flights": 12836, "delays": 1165}, "AS": {"flights": 2698, "delays": 277}, "DL": {"flights": 965, "delays": 172}, "UA": {"flights": 2113, "delays": 402}, "US": {"flights": 296, "delays": 24}, "AA": {"flights": 1564, "delays": 194}, "VX": {"flights": 29, "delays": 4}}}, {"name_iata": "OKC", "name": "Will Rogers World Airport", "airlines": {"AA": {"flights": 1650, "delays": 198}, "DL": {"flights": 1489, "delays": 140}, "OO": {"flights": 2561, "delays": 438}, "WN": {"flights": 5762, "delays": 909}, "MQ": {"flights": 2006, "delays": 460}, "EV": {"flights": 1739, "delays": 299}, "UA": {"flights": 585, "delays": 92}, "F9": {"flights": 52, "delays": 15}}}, {"name_iata": "OMA", "name": "Eppley Airfield", "airlines": {"OO": {"flights": 2140, "delays": 335}, "UA": {"flights": 1119, "delays": 239}, "AA": {"flights": 1537, "delays": 161}, "F9": {"flights": 276, "delays": 50}, "DL": {"flights": 2165, "delays": 180}, "US": {"flights": 343, "delays": 26}, "WN": {"flights": 5222, "delays": 900}, "EV": {"flights": 2854, "delays": 444}, "MQ": {"flights": 834, "delays": 148}}}, {"name_iata": "OME", "name": "Nome Airport", "airlines": {"AS": {"flights": 636, "delays": 119}}}, {"name_iata": "ONT", "name": "Ontario International Airport", "airlines": {"OO": {"flights": 4949, "delays": 787}, "WN": {"flights": 9608, "delays": 1916}, "AS": {"flights": 523, "delays": 42}, "US": {"flights": 592, "delays": 45}, "AA": {"flights": 1913, "delays": 271}, "DL": {"flights": 211, "delays": 10}}}, {"name_iata": "ORD", "name": "Chicago O'Hare International Airport", "airlines": {"US": {"flights": 3355, "delays": 506}, "UA": {"flights": 58471, "delays": 17059}, "NK": {"flights": 9696, "delays": 3590}, "EV": {"flights": 42766, "delays": 7860}, "B6": {"flights": 2214, "delays": 580}, "DL": {"flights": 6935, "delays": 1371}, "OO": {"flights": 36552, "delays": 8667}, "F9": {"flights": 4565, "delays": 1427}, "AS": {"flights": 1739, "delays": 234}, "AA": {"flights": 49733, "delays": 11020}, "VX": {"flights": 1373, "delays": 274}, "MQ": {"flights": 59937, "delays": 12826}}}, {"name_iata": "ORF", "name": "Norfolk International Airport", "airlines": {"MQ": {"flights": 635, "delays": 138}, "DL": {"flights": 2705, "delays": 274}, "AA": {"flights": 1013, "delays": 131}, "US": {"flights": 200, "delays": 11}, "OO": {"flights": 471, "delays": 115}, "WN": {"flights": 2085, "delays": 396}, "EV": {"flights": 1903, "delays": 358}, "UA": {"flights": 99, "delays": 16}}}, {"name_iata": "ORH", "name": "Worcester Regional Airport", "airlines": {"B6": {"flights": 637, "delays": 94}}}, {"name_iata": "OTH", "name": "Southwest Oregon Regional Airport\u00a0(North Bend Municipal)", "airlines": {"OO": {"flights": 265, "delays": 74}}}, {"name_iata": "OTZ", "name": "Ralph Wien Memorial Airport", "airlines": {"AS": {"flights": 641, "delays": 110}}}, {"name_iata": "PAH", "name": "Barkley Regional Airport", "airlines": {"OO": {"flights": 622, "delays": 74}}}, {"name_iata": "PBG", "name": "Plattsburgh International Airport", "airlines": {"NK": {"flights": 279, "delays": 76}}}, {"name_iata": "PBI", "name": "Palm Beach International Airport", "airlines": {"UA": {"flights": 2042, "delays": 473}, "B6": {"flights": 6592, "delays": 1999}, "AA": {"flights": 2883, "delays": 422}, "DL": {"flights": 5662, "delays": 941}, "WN": {"flights": 2507, "delays": 564}, "US": {"flights": 1827, "delays": 226}, "NK": {"flights": 304, "delays": 61}, "F9": {"flights": 184, "delays": 61}, "OO": {"flights": 76, "delays": 18}, "EV": {"flights": 142, "delays": 40}}}, {"name_iata": "PDX", "name": "Portland International Airport", "airlines": {"DL": {"flights": 5428, "delays": 549}, "US": {"flights": 1017, "delays": 75}, "UA": {"flights": 5195, "delays": 801}, "AA": {"flights": 2695, "delays": 327}, "AS": {"flights": 12847, "delays": 1205}, "NK": {"flights": 650, "delays": 187}, "WN": {"flights": 10885, "delays": 1924}, "OO": {"flights": 5343, "delays": 648}, "B6": {"flights": 1296, "delays": 220}, "F9": {"flights": 841, "delays": 98}, "HA": {"flights": 334, "delays": 26}, "VX": {"flights": 342, "delays": 18}}}, {"name_iata": "PHF", "name": "Newport News/Williamsburg International Airport", "airlines": {"EV": {"flights": 1152, "delays": 199}, "F9": {"flights": 3, "delays": 1}, "DL": {"flights": 81, "delays": 6}}}, {"name_iata": "PHL", "name": "Philadelphia International Airport", "airlines": {"UA": {"flights": 3641, "delays": 758}, "F9": {"flights": 2571, "delays": 780}, "DL": {"flights": 6523, "delays": 1023}, "AA": {"flights": 20941, "delays": 3313}, "US": {"flights": 19997, "delays": 3766}, "WN": {"flights": 8003, "delays": 1555}, "B6": {"flights": 1566, "delays": 334}, "AS": {"flights": 333, "delays": 57}, "NK": {"flights": 1215, "delays": 343}, "EV": {"flights": 138, "delays": 28}, "OO": {"flights": 10, "delays": 2}, "MQ": {"flights": 9, "delays": 2}}}, {"name_iata": "PHX", "name": "Phoenix Sky Harbor International Airport", "airlines": {"NK": {"flights": 941, "delays": 263}, "AA": {"flights": 28074, "delays": 4262}, "US": {"flights": 27626, "delays": 3954}, "DL": {"flights": 6906, "delays": 694}, "UA": {"flights": 5425, "delays": 941}, "WN": {"flights": 53487, "delays": 12912}, "AS": {"flights": 2274, "delays": 190}, "F9": {"flights": 1855, "delays": 464}, "OO": {"flights": 18329, "delays": 2378}, "HA": {"flights": 334, "delays": 14}, "EV": {"flights": 8, "delays": 0}, "B6": {"flights": 654, "delays": 215}}}, {"name_iata": "PIA", "name": "General Wayne A. Downing Peoria International Airport", "airlines": {"EV": {"flights": 2468, "delays": 361}, "MQ": {"flights": 1753, "delays": 244}, "OO": {"flights": 288, "delays": 65}}}, {"name_iata": "PIB", "name": "Hattiesburg-Laurel Regional Airport", "airlines": {"EV": {"flights": 566, "delays": 76}}}, {"name_iata": "PIH", "name": "Pocatello Regional Airport", "airlines": {"OO": {"flights": 652, "delays": 30}}}, {"name_iata": "PIT", "name": "Pittsburgh International Airport", "airlines": {"UA": {"flights": 2241, "delays": 370}, "WN": {"flights": 8602, "delays": 1200}, "DL": {"flights": 3481, "delays": 448}, "AA": {"flights": 3278, "delays": 323}, "US": {"flights": 2314, "delays": 250}, "B6": {"flights": 1468, "delays": 213}, "EV": {"flights": 1310, "delays": 232}, "MQ": {"flights": 570, "delays": 123}, "OO": {"flights": 466, "delays": 89}}}, {"name_iata": "PLN", "name": "Pellston Regional Airport of Emmet County", "airlines": {"OO": {"flights": 732, "delays": 87}}}, {"name_iata": "PNS", "name": "Pensacola International Airport\u00a0(Pensacola Gulf Coast Regional Airport)", "airlines": {"DL": {"flights": 2253, "delays": 271}, "MQ": {"flights": 1132, "delays": 228}, "EV": {"flights": 1780, "delays": 257}, "WN": {"flights": 953, "delays": 180}, "AA": {"flights": 308, "delays": 59}}}, {"name_iata": "PPG", "name": "Pago Pago International Airport (Tafuna Airport)", "airlines": {"HA": {"flights": 107, "delays": 18}}}, {"name_iata": "PSC", "name": "Tri-Cities Airport", "airlines": {"OO": {"flights": 2100, "delays": 217}, "DL": {"flights": 304, "delays": 11}}}, {"name_iata": "PSE", "name": "Mercedita Airport", "airlines": {"B6": {"flights": 738, "delays": 109}}}, {"name_iata": "PSG", "name": "Petersburg James A. Johnson Airport", "airlines": {"AS": {"flights": 655, "delays": 115}}}, {"name_iata": "PSP", "name": "Palm Springs International Airport", "airlines": {"OO": {"flights": 5480, "delays": 972}, "AS": {"flights": 1623, "delays": 168}, "AA": {"flights": 959, "delays": 139}, "F9": {"flights": 4, "delays": 2}, "VX": {"flights": 210, "delays": 48}, "DL": {"flights": 154, "delays": 32}, "UA": {"flights": 456, "delays": 87}}}, {"name_iata": "PUB", "name": "Pueblo Memorial Airport", "airlines": {"OO": {"flights": 253, "delays": 36}}}, {"name_iata": "PVD", "name": "Theodore Francis Green State Airport", "airlines": {"US": {"flights": 573, "delays": 71}, "WN": {"flights": 5841, "delays": 900}, "B6": {"flights": 975, "delays": 173}, "EV": {"flights": 1023, "delays": 204}, "DL": {"flights": 1456, "delays": 144}, "OO": {"flights": 37, "delays": 4}, "UA": {"flights": 110, "delays": 22}, "AA": {"flights": 776, "delays": 65}}}, {"name_iata": "PWM", "name": "Portland International Jetport", "airlines": {"B6": {"flights": 1139, "delays": 190}, "US": {"flights": 172, "delays": 21}, "WN": {"flights": 994, "delays": 165}, "DL": {"flights": 671, "delays": 86}, "EV": {"flights": 1375, "delays": 257}, "AA": {"flights": 192, "delays": 13}}}, {"name_iata": "RAP", "name": "Rapid City Regional Airport", "airlines": {"OO": {"flights": 2240, "delays": 296}, "EV": {"flights": 316, "delays": 56}, "MQ": {"flights": 491, "delays": 80}, "DL": {"flights": 170, "delays": 12}}}, {"name_iata": "RDD", "name": "Redding Municipal Airport", "airlines": {"OO": {"flights": 706, "delays": 119}}}, {"name_iata": "RDM", "name": "Redmond Municipal Airport\u00a0(Roberts Field)", "airlines": {"OO": {"flights": 2122, "delays": 248}}}, {"name_iata": "RDU", "name": "Raleigh-Durham International Airport", "airlines": {"MQ": {"flights": 2280, "delays": 602}, "DL": {"flights": 5074, "delays": 652}, "AA": {"flights": 5321, "delays": 802}, "UA": {"flights": 1493, "delays": 363}, "B6": {"flights": 2531, "delays": 501}, "US": {"flights": 1699, "delays": 221}, "WN": {"flights": 9256, "delays": 1536}, "OO": {"flights": 296, "delays": 51}, "F9": {"flights": 731, "delays": 133}, "EV": {"flights": 2413, "delays": 435}, "AS": {"flights": 61, "delays": 8}}}, {"name_iata": "RHI", "name": "Rhinelander-Oneida County Airport", "airlines": {"OO": {"flights": 939, "delays": 104}}}, {"name_iata": "RIC", "name": "Richmond International Airport", "airlines": {"EV": {"flights": 5096, "delays": 1034}, "DL": {"flights": 2572, "delays": 373}, "MQ": {"flights": 1383, "delays": 315}, "AA": {"flights": 1457, "delays": 231}, "US": {"flights": 664, "delays": 66}, "WN": {"flights": 1303, "delays": 164}, "B6": {"flights": 2076, "delays": 276}, "UA": {"flights": 301, "delays": 49}, "OO": {"flights": 80, "delays": 25}}}, {"name_iata": "RKS", "name": "Rock Springs-Sweetwater County Airport", "airlines": {"OO": {"flights": 672, "delays": 67}}}, {"name_iata": "RNO", "name": "Reno/Tahoe International Airport", "airlines": {"UA": {"flights": 793, "delays": 95}, "DL": {"flights": 929, "delays": 65}, "US": {"flights": 567, "delays": 62}, "OO": {"flights": 2631, "delays": 600}, "AA": {"flights": 1617, "delays": 223}, "WN": {"flights": 6173, "delays": 1064}, "B6": {"flights": 168, "delays": 56}}}, {"name_iata": "ROA", "name": "Roanoke Regional Airport\u00a0(Woodrum Field)", "airlines": {"EV": {"flights": 1837, "delays": 325}, "DL": {"flights": 386, "delays": 38}}}, {"name_iata": "ROC", "name": "Greater Rochester International Airport", "airlines": {"B6": {"flights": 1071, "delays": 172}, "DL": {"flights": 1227, "delays": 127}, "EV": {"flights": 1445, "delays": 241}, "WN": {"flights": 1909, "delays": 310}, "US": {"flights": 154, "delays": 21}, "MQ": {"flights": 900, "delays": 148}, "UA": {"flights": 404, "delays": 64}, "AA": {"flights": 153, "delays": 10}}}, {"name_iata": "ROW", "name": "Roswell International Air Center", "airlines": {"MQ": {"flights": 913, "delays": 134}, "EV": {"flights": 6, "delays": 4}}}, {"name_iata": "RST", "name": "Rochester International Airport", "airlines": {"MQ": {"flights": 1256, "delays": 173}, "EV": {"flights": 683, "delays": 108}, "OO": {"flights": 36, "delays": 9}}}, {"name_iata": "RSW", "name": "Southwest Florida International Airport", "airlines": {"UA": {"flights": 2339, "delays": 361}, "B6": {"flights": 3946, "delays": 1039}, "NK": {"flights": 2185, "delays": 589}, "F9": {"flights": 1341, "delays": 335}, "DL": {"flights": 5502, "delays": 595}, "AA": {"flights": 2815, "delays": 384}, "WN": {"flights": 6993, "delays": 1180}, "US": {"flights": 1803, "delays": 228}, "EV": {"flights": 53, "delays": 10}, "OO": {"flights": 47, "delays": 13}}}, {"name_iata": "SAF", "name": "Santa Fe Municipal Airport", "airlines": {"EV": {"flights": 515, "delays": 94}, "OO": {"flights": 219, "delays": 36}, "MQ": {"flights": 710, "delays": 110}}}, {"name_iata": "SAN", "name": "San Diego International Airport\u00a0(Lindbergh Field)", "airlines": {"DL": {"flights": 5843, "delays": 428}, "OO": {"flights": 6339, "delays": 1045}, "WN": {"flights": 30469, "delays": 6863}, "UA": {"flights": 7618, "delays": 1361}, "AA": {"flights": 6466, "delays": 721}, "US": {"flights": 1704, "delays": 163}, "AS": {"flights": 5128, "delays": 344}, "NK": {"flights": 1811, "delays": 291}, "VX": {"flights": 1727, "delays": 384}, "F9": {"flights": 742, "delays": 124}, "HA": {"flights": 334, "delays": 28}, "B6": {"flights": 1241, "delays": 291}}}, {"name_iata": "SAT", "name": "San Antonio International Airport", "airlines": {"AA": {"flights": 5108, "delays": 660}, "OO": {"flights": 3431, "delays": 629}, "UA": {"flights": 2671, "delays": 399}, "WN": {"flights": 13722, "delays": 2481}, "DL": {"flights": 2988, "delays": 283}, "US": {"flights": 327, "delays": 34}, "EV": {"flights": 780, "delays": 116}, "AS": {"flights": 333, "delays": 46}, "MQ": {"flights": 97, "delays": 27}}}, {"name_iata": "SAV", "name": "Savannah/Hilton Head International Airport", "airlines": {"EV": {"flights": 2677, "delays": 568}, "DL": {"flights": 3129, "delays": 382}, "B6": {"flights": 982, "delays": 242}, "MQ": {"flights": 570, "delays": 117}, "OO": {"flights": 39, "delays": 8}}}, {"name_iata": "SBA", "name": "Santa Barbara Municipal Airport\u00a0(Santa Barbara Airport)", "airlines": {"OO": {"flights": 5887, "delays": 938}, "F9": {"flights": 3, "delays": 2}}}, {"name_iata": "SBN", "name": "South Bend International Airport\u00a0(South Bend Regional)", "airlines": {"EV": {"flights": 987, "delays": 161}, "OO": {"flights": 3352, "delays": 524}, "DL": {"flights": 14, "delays": 2}}}, {"name_iata": "SBP", "name": "San Luis Obispo County Regional Airport\u00a0(McChesney Field)", "airlines": {"OO": {"flights": 3068, "delays": 487}}}, {"name_iata": "SCC", "name": "Deadhorse Airport\u00a0(Prudhoe Bay Airport)", "airlines": {"AS": {"flights": 837, "delays": 102}}}, {"name_iata": "SCE", "name": "University Park Airport", "airlines": {"EV": {"flights": 886, "delays": 126}}}, {"name_iata": "SDF", "name": "Louisville International Airport\u00a0(Standiford Field)", "airlines": {"DL": {"flights": 2669, "delays": 298}, "WN": {"flights": 3990, "delays": 600}, "EV": {"flights": 1996, "delays": 403}, "MQ": {"flights": 684, "delays": 160}, "AA": {"flights": 289, "delays": 58}, "OO": {"flights": 320, "delays": 75}, "UA": {"flights": 17, "delays": 1}, "US": {"flights": 8, "delays": 1}}}, {"name_iata": "SEA", "name": "Seattle-Tacoma International Airport", "airlines": {"AS": {"flights": 49930, "delays": 5729}, "DL": {"flights": 13528, "delays": 2030}, "AA": {"flights": 6341, "delays": 886}, "US": {"flights": 1580, "delays": 164}, "UA": {"flights": 8722, "delays": 1796}, "F9": {"flights": 791, "delays": 167}, "WN": {"flights": 11655, "delays": 2495}, "OO": {"flights": 12996, "delays": 2057}, "HA": {"flights": 668, "delays": 47}, "VX": {"flights": 2121, "delays": 483}, "B6": {"flights": 2117, "delays": 604}}}, {"name_iata": "SFO", "name": "San Francisco International Airport", "airlines": {"US": {"flights": 2592, "delays": 257}, "DL": {"flights": 9658, "delays": 1543}, "AA": {"flights": 12059, "delays": 1887}, "UA": {"flights": 45105, "delays": 10444}, "WN": {"flights": 13788, "delays": 3038}, "F9": {"flights": 1942, "delays": 441}, "B6": {"flights": 4889, "delays": 1088}, "OO": {"flights": 34171, "delays": 7159}, "VX": {"flights": 15848, "delays": 2644}, "AS": {"flights": 5144, "delays": 870}, "HA": {"flights": 664, "delays": 61}}}, {"name_iata": "SGF", "name": "Springfield-Branson National Airport", "airlines": {"MQ": {"flights": 3483, "delays": 579}, "DL": {"flights": 333, "delays": 16}, "OO": {"flights": 697, "delays": 136}, "EV": {"flights": 1549, "delays": 298}}}, {"name_iata": "SGU", "name": "St. George Regional Airport", "airlines": {"OO": {"flights": 1771, "delays": 171}}}, {"name_iata": "SHV", "name": "Shreveport Regional Airport", "airlines": {"EV": {"flights": 5140, "delays": 888}, "MQ": {"flights": 225, "delays": 52}, "DL": {"flights": 271, "delays": 36}, "OO": {"flights": 313, "delays": 66}}}, {"name_iata": "SIT", "name": "Sitka Rocky Gutierrez Airport", "airlines": {"AS": {"flights": 1221, "delays": 142}, "OO": {"flights": 112, "delays": 7}}}, {"name_iata": "SJC", "name": "Norman Y. Mineta San Jos\u00e9 International Airport", "airlines": {"OO": {"flights": 5509, "delays": 748}, "US": {"flights": 784, "delays": 72}, "DL": {"flights": 1314, "delays": 151}, "WN": {"flights": 20997, "delays": 4338}, "AS": {"flights": 4130, "delays": 310}, "AA": {"flights": 2831, "delays": 281}, "HA": {"flights": 663, "delays": 49}, "UA": {"flights": 1041, "delays": 116}, "B6": {"flights": 493, "delays": 156}}}, {"name_iata": "SJT", "name": "San Angelo Regional Airport\u00a0(Mathis Field)", "airlines": {"MQ": {"flights": 1406, "delays": 209}, "EV": {"flights": 145, "delays": 41}}}, {"name_iata": "SJU", "name": "Luis Mu\u00f1oz Mar\u00edn International Airport", "airlines": {"UA": {"flights": 1854, "delays": 556}, "B6": {"flights": 10253, "delays": 2429}, "AA": {"flights": 4672, "delays": 683}, "WN": {"flights": 3099, "delays": 344}, "DL": {"flights": 3012, "delays": 339}, "US": {"flights": 1030, "delays": 202}, "NK": {"flights": 545, "delays": 138}}}, {"name_iata": "SLC", "name": "Salt Lake City International Airport", "airlines": {"DL": {"flights": 33255, "delays": 3793}, "OO": {"flights": 44291, "delays": 4727}, "AA": {"flights": 2969, "delays": 417}, "F9": {"flights": 1278, "delays": 277}, "AS": {"flights": 2077, "delays": 163}, "US": {"flights": 1241, "delays": 117}, "WN": {"flights": 8807, "delays": 1642}, "UA": {"flights": 1409, "delays": 278}, "B6": {"flights": 1371, "delays": 356}, "EV": {"flights": 54, "delays": 17}, "MQ": {"flights": 63, "delays": 10}}}, {"name_iata": "SMF", "name": "Sacramento International Airport", "airlines": {"UA": {"flights": 2217, "delays": 317}, "US": {"flights": 986, "delays": 130}, "AA": {"flights": 2162, "delays": 296}, "OO": {"flights": 5949, "delays": 1048}, "DL": {"flights": 1844, "delays": 270}, "WN": {"flights": 20277, "delays": 3653}, "AS": {"flights": 2101, "delays": 151}, "B6": {"flights": 984, "delays": 192}, "HA": {"flights": 334, "delays": 28}}}, {"name_iata": "SMX", "name": "Santa Maria Public Airport\u00a0(Capt G. Allan Hancock Field)", "airlines": {"OO": {"flights": 652, "delays": 94}}}, {"name_iata": "SNA", "name": "John Wayne Airport\u00a0(Orange County Airport)", "airlines": {"UA": {"flights": 5003, "delays": 884}, "US": {"flights": 765, "delays": 56}, "AA": {"flights": 4894, "delays": 556}, "DL": {"flights": 2538, "delays": 195}, "F9": {"flights": 765, "delays": 114}, "OO": {"flights": 2520, "delays": 456}, "AS": {"flights": 3269, "delays": 238}, "WN": {"flights": 17047, "delays": 3039}}}, {"name_iata": "SPI", "name": "Abraham Lincoln Capital Airport", "airlines": {"OO": {"flights": 956, "delays": 152}, "MQ": {"flights": 234, "delays": 39}, "EV": {"flights": 332, "delays": 29}}}, {"name_iata": "SPS", "name": "Wichita Falls Municipal Airport/Sheppard AFB", "airlines": {"MQ": {"flights": 924, "delays": 140}, "EV": {"flights": 249, "delays": 46}}}, {"name_iata": "SRQ", "name": "Sarasota-Bradenton International Airport", "airlines": {"DL": {"flights": 2098, "delays": 239}, "B6": {"flights": 828, "delays": 246}, "UA": {"flights": 405, "delays": 90}}}, {"name_iata": "STC", "name": "St. Cloud Regional Airport", "airlines": {"OO": {"flights": 78, "delays": 25}}}, {"name_iata": "STL", "name": "St. Louis International Airport at Lambert Field", "airlines": {"AA": {"flights": 5846, "delays": 756}, "DL": {"flights": 4633, "delays": 486}, "WN": {"flights": 27445, "delays": 5827}, "US": {"flights": 1077, "delays": 169}, "OO": {"flights": 1498, "delays": 273}, "MQ": {"flights": 1215, "delays": 351}, "EV": {"flights": 3038, "delays": 565}, "F9": {"flights": 870, "delays": 134}, "UA": {"flights": 296, "delays": 107}, "AS": {"flights": 398, "delays": 58}}}, {"name_iata": "STT", "name": "Cyril E. King Airport", "airlines": {"DL": {"flights": 934, "delays": 114}, "AA": {"flights": 1388, "delays": 292}, "B6": {"flights": 862, "delays": 148}, "UA": {"flights": 448, "delays": 125}, "US": {"flights": 360, "delays": 77}, "NK": {"flights": 307, "delays": 77}}}, {"name_iata": "STX", "name": "Henry E. Rohlsen Airport", "airlines": {"AA": {"flights": 545, "delays": 83}, "B6": {"flights": 333, "delays": 67}, "DL": {"flights": 37, "delays": 8}, "US": {"flights": 21, "delays": 11}}}, {"name_iata": "SUN", "name": "Friedman Memorial Airport", "airlines": {"OO": {"flights": 868, "delays": 105}}}, {"name_iata": "SUX", "name": "Sioux Gateway Airport", "airlines": {"MQ": {"flights": 591, "delays": 96}}}, {"name_iata": "SWF", "name": "Stewart International Airport", "airlines": {"B6": {"flights": 663, "delays": 115}, "EV": {"flights": 20, "delays": 7}}}, {"name_iata": "SYR", "name": "Syracuse Hancock International Airport", "airlines": {"B6": {"flights": 1311, "delays": 201}, "EV": {"flights": 1233, "delays": 176}, "US": {"flights": 316, "delays": 28}, "MQ": {"flights": 1069, "delays": 191}, "DL": {"flights": 1144, "delays": 122}, "OO": {"flights": 118, "delays": 30}, "AA": {"flights": 271, "delays": 22}}}, {"name_iata": "TLH", "name": "Tallahassee International Airport", "airlines": {"MQ": {"flights": 709, "delays": 98}, "DL": {"flights": 1236, "delays": 102}, "EV": {"flights": 1207, "delays": 234}}}, {"name_iata": "TOL", "name": "Toledo Express Airport", "airlines": {"MQ": {"flights": 897, "delays": 109}}}, {"name_iata": "TPA", "name": "Tampa International Airport", "airlines": {"UA": {"flights": 5783, "delays": 1012}, "AA": {"flights": 8130, "delays": 1157}, "B6": {"flights": 5422, "delays": 1397}, "DL": {"flights": 10349, "delays": 1444}, "F9": {"flights": 1524, "delays": 399}, "US": {"flights": 3509, "delays": 389}, "WN": {"flights": 25657, "delays": 4900}, "NK": {"flights": 2574, "delays": 658}, "AS": {"flights": 334, "delays": 63}}}, {"name_iata": "TRI", "name": "Tri-Cities Regional Airport", "airlines": {"DL": {"flights": 476, "delays": 32}, "EV": {"flights": 1431, "delays": 218}}}, {"name_iata": "TTN", "name": "Trenton Mercer Airport", "airlines": {"F9": {"flights": 2779, "delays": 581}}}, {"name_iata": "TUL", "name": "Tulsa International Airport", "airlines": {"AA": {"flights": 2278, "delays": 285}, "DL": {"flights": 1038, "delays": 101}, "WN": {"flights": 4067, "delays": 745}, "EV": {"flights": 3340, "delays": 451}, "OO": {"flights": 1488, "delays": 230}, "MQ": {"flights": 1377, "delays": 301}, "VX": {"flights": 1, "delays": 1}, "UA": {"flights": 150, "delays": 19}}}, {"name_iata": "TUS", "name": "Tucson International Airport", "airlines": {"OO": {"flights": 6335, "delays": 945}, "EV": {"flights": 526, "delays": 79}, "WN": {"flights": 4181, "delays": 701}, "AA": {"flights": 2726, "delays": 306}, "DL": {"flights": 793, "delays": 73}, "AS": {"flights": 346, "delays": 19}, "US": {"flights": 3, "delays": 1}, "UA": {"flights": 53, "delays": 12}}}, {"name_iata": "TVC", "name": "Cherry Capital Airport", "airlines": {"EV": {"flights": 857, "delays": 131}, "MQ": {"flights": 1043, "delays": 134}, "OO": {"flights": 339, "delays": 34}, "DL": {"flights": 425, "delays": 26}}}, {"name_iata": "TWF", "name": "Magic Valley Regional Airport\u00a0(Joslin Field)", "airlines": {"OO": {"flights": 806, "delays": 47}}}, {"name_iata": "TXK", "name": "Texarkana Regional Airport\u00a0(Webb Field)", "airlines": {"MQ": {"flights": 471, "delays": 73}, "EV": {"flights": 447, "delays": 50}}}, {"name_iata": "TYR", "name": "Tyler Pounds Regional Airport", "airlines": {"EV": {"flights": 1640, "delays": 230}, "MQ": {"flights": 560, "delays": 116}}}, {"name_iata": "TYS", "name": "McGhee Tyson Airport", "airlines": {"EV": {"flights": 4845, "delays": 902}, "MQ": {"flights": 840, "delays": 217}, "DL": {"flights": 930, "delays": 86}, "F9": {"flights": 103, "delays": 19}, "OO": {"flights": 73, "delays": 18}}}, {"name_iata": "UST", "name": "Northeast Florida Regional Airport\u00a0(St. Augustine Airport)", "airlines": {"F9": {"flights": 144, "delays": 44}}}, {"name_iata": "VEL", "name": "Valdez Airport", "airlines": {"OO": {"flights": 200, "delays": 5}}}, {"name_iata": "VLD", "name": "Valdosta Regional Airport", "airlines": {"EV": {"flights": 927, "delays": 119}}}, {"name_iata": "VPS", "name": "Destin-Fort Walton Beach Airport/Eglin AFB", "airlines": {"EV": {"flights": 2473, "delays": 442}, "MQ": {"flights": 477, "delays": 118}, "DL": {"flights": 1755, "delays": 172}, "OO": {"flights": 64, "delays": 15}}}, {"name_iata": "WRG", "name": "Wrangell Airport", "airlines": {"AS": {"flights": 653, "delays": 101}}}, {"name_iata": "WYS", "name": "Westerly State Airport", "airlines": {"OO": {"flights": 208, "delays": 11}}}, {"name_iata": "XNA", "name": "Northwest Arkansas Regional Airport", "airlines": {"MQ": {"flights": 4253, "delays": 938}, "EV": {"flights": 2928, "delays": 496}, "OO": {"flights": 1252, "delays": 196}, "DL": {"flights": 536, "delays": 32}, "AA": {"flights": 18, "delays": 0}}}, {"name_iata": "YAK", "name": "Yakutat Airport", "airlines": {"AS": {"flights": 657, "delays": 69}}}, {"name_iata": "YUM", "name": "Yuma International Airport", "airlines": {"OO": {"flights": 1854, "delays": 151}}}]